pycounts_ts_mds/__init__.py
pycounts_ts_mds/plotting.py
pycounts_ts_mds/pycounts_ts_mds.py
pycounts_ts_mds-0.2.0.dist-info/LICENSE
pycounts_ts_mds-0.2.0.dist-info/METADATA
pycounts_ts_mds-0.2.0.dist-info/WHEEL
pycounts_ts_mds-0.2.0.dist-info/RECORD
