Metadata-Version: 2.3
Name: pycounts_ts_mds
Version: 0.2.0
Summary: A short test package that counts the words in a given file.
License: MIT
Author: Timothy Singh
Requires-Python: >=3.11
Classifier: License :: OSI Approved :: MIT License
Classifier: Programming Language :: Python :: 3
Classifier: Programming Language :: Python :: 3.11
Classifier: Programming Language :: Python :: 3.12
Classifier: Programming Language :: Python :: 3.13
Requires-Dist: matplotlib (>=3.10.0)
